[
  {
    "sessionId": "04d73579-9d7d-41ec-a800-074dd10866e7",
    "reason": "other",
    "endedAt": "2026-07-08T03:48:03.104Z",
    "feature": null,
    "phase": null,
    "progress": null
  },
  {
    "sessionId": "c80c8549-17c1-459b-98ae-7c1a74bb43ea",
    "reason": "other",
    "endedAt": "2026-07-10T05:42:03.131Z",
    "feature": null,
    "phase": null,
    "progress": null
  },
  {
    "sessionId": "04d73579-9d7d-41ec-a800-074dd10866e7",
    "reason": "other",
    "endedAt": "2026-07-10T05:57:06.738Z",
    "feature": null,
    "phase": null,
    "progress": null
  },
  {
    "sessionId": "f788c8ea-2c99-4f82-8872-26e03a52b2a0",
    "reason": "other",
    "endedAt": "2026-07-10T06:28:31.454Z",
    "feature": null,
    "phase": null,
    "progress": null
  },
  {
    "sessionId": "ef374f02-73ce-40c4-82ca-c361c7d1a31c",
    "reason": "other",
    "endedAt": "2026-07-10T22:08:08.263Z",
    "feature": null,
    "phase": null,
    "progress": null
  },
  {
    "sessionId": "f788c8ea-2c99-4f82-8872-26e03a52b2a0",
    "reason": "other",
    "endedAt": "2026-07-10T22:32:23.498Z",
    "feature": null,
    "phase": null,
    "progress": null
  },
  {
    "sessionId": "f788c8ea-2c99-4f82-8872-26e03a52b2a0",
    "reason": "other",
    "endedAt": "2026-07-11T00:36:30.168Z",
    "feature": null,
    "phase": null,
    "progress": null
  },
  {
    "sessionId": "435d1b67-b438-427f-a263-ac48b89c41fd",
    "reason": "other",
    "endedAt": "2026-07-11T03:29:06.422Z",
    "feature": null,
    "phase": null,
    "progress": null
  },
  {
    "sessionId": "b662000e-0fe0-4c86-934b-3deddf0720b2",
    "reason": "other",
    "endedAt": "2026-07-11T23:33:10.493Z",
    "feature": null,
    "phase": null,
    "progress": null
  },
  {
    "sessionId": "cff750ec-62eb-4797-9953-7a3b53a3f735",
    "reason": "other",
    "endedAt": "2026-07-11T23:59:28.216Z",
    "feature": null,
    "phase": null,
    "progress": null
  },
  {
    "sessionId": "918501a5-6c5b-44b1-aede-e680c55915d1",
    "reason": "other",
    "endedAt": "2026-07-12T02:58:22.836Z",
    "feature": null,
    "phase": null,
    "progress": null
  },
  {
    "sessionId": "6608ddad-0d6b-4e37-9844-da0e46d1b212",
    "reason": "other",
    "endedAt": "2026-07-12T03:37:02.234Z",
    "feature": null,
    "phase": null,
    "progress": null
  },
  {
    "sessionId": "3eb60a16-71e7-44b3-b850-90a3296e8485",
    "reason": "other",
    "endedAt": "2026-07-13T02:56:35.268Z",
    "feature": null,
    "phase": null,
    "progress": null
  },
  {
    "sessionId": "94cf7fc8-c39c-4a6c-911e-c80e3c8cd243",
    "reason": "other",
    "endedAt": "2026-07-14T03:20:49.201Z",
    "feature": null,
    "phase": null,
    "progress": null
  },
  {
    "sessionId": "e8cf3a65-cb13-4e1b-9833-7b88840af519",
    "reason": "other",
    "endedAt": "2026-07-14T03:22:02.127Z",
    "feature": null,
    "phase": null,
    "progress": null
  },
  {
    "sessionId": "9207526f-cbad-4eb0-b296-7606eb2ba836",
    "reason": "other",
    "endedAt": "2026-07-15T02:59:38.019Z",
    "feature": null,
    "phase": null,
    "progress": null
  },
  {
    "sessionId": "9f362868-d8b3-49a5-ac60-307e3bd7a54d",
    "reason": "other",
    "endedAt": "2026-07-15T03:03:32.583Z",
    "feature": null,
    "phase": null,
    "progress": null
  },
  {
    "sessionId": "6608ddad-0d6b-4e37-9844-da0e46d1b212",
    "reason": "other",
    "endedAt": "2026-07-15T04:38:52.783Z",
    "feature": null,
    "phase": null,
    "progress": null
  },
  {
    "sessionId": "cff750ec-62eb-4797-9953-7a3b53a3f735",
    "reason": "other",
    "endedAt": "2026-07-15T04:38:57.420Z",
    "feature": null,
    "phase": null,
    "progress": null
  },
  {
    "sessionId": "341b652a-617b-474c-9f48-cdd965648f05",
    "reason": "other",
    "endedAt": "2026-07-16T03:31:42.599Z",
    "feature": null,
    "phase": null,
    "progress": null
  }
]